{
 "version": "1.0.2",
 "name": "Park",
 "props": [
  {
   "assetPath": "background/park_bg_1",
   "atlasSettings": null,
   "name": "BG",
   "position": [-825, -200],
   "scale": 1,
   "startingAnimation": ""
  }
 ],
 "characters": {
  "bf": {
   "cameraOffsets": [-70, -90],
   "position": [980, 915],
   "zIndex": 300
  },
  "dad": {
   "cameraOffsets": [90, -60],
   "position": [255, 825],
   "zIndex": 200
  },
  "gf": {
   "cameraOffsets": [0, 0],
   "position": [745, 804],
   "zIndex": 100
  }
 },
 "cameraZoom": 0.9
}